dflipflop/d.v
module d_flipflop(input d,clk,rst,
output reg q,
output qbar);
assign qbar=~q;
always @ (posedge clk)begin
    if(!rst)
    q<=0;
    else 
    q<=d;
end 
endmodule

dflipflop/d_tb.v
module test;
reg d,clk,rst;
wire q,qbar;

d_flipflop dut (d,clk,rst,q,qbar);

// clock generation
always #2 clk = ~clk;

initial begin
    // initialize
    clk = 0;
    rst = 0;
    d = 0;

    // small delay then check
    #5 $display("reset::rst=%0d d=%0d q=%0d qbar=%0d",d,rst,q,qbar);

    // assert reset
    #4 rst = 1;

    // first set of random inputs
    repeat(5) begin
        @(posedge clk);
        d = $urandom_range(0,1); // or d = $random % 2;
        #1 $display("d=%0h,q=%0h qbar=%0h",d,q,qbar);
        rst = 0;
        #5 $display("reset::rst=%0d d=%0d q=%0d qbar=%0d",d,rst,q,qbar);
    end

    // assert reset again
    #4 rst = 1;

    // second set of random inputs
    repeat(5) begin
        @(posedge clk);
        d = $urandom_range(0,1); // or $random % 2
        #1 $display("d=%0h,q=%0h qbar=%0h",d,q,qbar);
    end

    #100 $finish;
end

initial begin
    $dumpfile("wave.vcd");
    $dumpvars(0,test);
end

endmodule

dflipflop/wave.vcd
$date
	Thu Sep 18 10:53:36 2025
$end
$version
	Icarus Verilog
$end
$timescale
	1s
$end
$scope module test $end
$var wire 1 ! qbar $end
$var wire 1 " q $end
$var reg 1 # clk $end
$var reg 1 $ d $end
$var reg 1 % rst $end
$scope module dut $end
$var wire 1 # clk $end
$var wire 1 $ d $end
$var wire 1 ! qbar $end
$var wire 1 % rst $end
$var reg 1 " q $end
$upscope $end
$upscope $end
$enddefinitions $end
$comment Show the parameter values. $end
$dumpall
$end
#0
$dumpvars
0%
0$
0#
x"
x!
$end
#2
1!
0"
1#
#4
0#
#6
1#
#8
0#
#9
1%
#10
0!
1"
1$
1#
#11
0%
#12
0#
#14
1!
0"
1#
#16
0#
#18
0$
1#
#20
0#
#22
1#
#24
0#
#26
1#
#28
0#
#30
1#
#32
0#
#34
1#
#36
0#
#38
1#
#40
0#
#42
1$
1#
#44
0#
#46
1#
#48
0#
#50
1#
#52
0#
1%
#54
0!
1"
1#
#56
0#
#58
1!
0"
0$
1#
#60
0#
#62
1#
#64
0#
#66
0!
1"
1$
1#
