4x16decoder/decoder.v
module decoder(input[3:0]d,
input e,
output [15:0]y);
assign y=e?1<<d:0;
endmodule

4x16decoder/decoder_tb.v
`timescale 1ns/1ns
module decoder_tb;

  reg [3:0] d;            // 4-bit input
  reg e;                  // enable
  wire [15:0] y;          // 16-bit one-hot output

  // Instantiate your 4x16 decoder module
  decoder dut (.d(d), .e(e), .y(y));

  integer i; // loop variable

  initial begin
    // dump waveform to view in GTKWave
    $dumpfile("wave.vcd");
    $dumpvars(0, decoder_tb);

    // Start with enable low
    e = 0; 
    d = 4'b0000;
    #1;

    // Enable low → output zero
    d = 4'b1011;
    #1;

    // Enable high
    e = 1;
    #1;

    // Loop through all input combinations
    for (i = 0; i < 16; i = i + 1) begin
      #1 d = i;
    end

    #10 $finish;
  end

  // Monitor signals on every change
  always @ (d or e or y)
    $display("time=%0t input:d=%b e=%b output:y=%b", $time, d, e, y);

endmodule

4x16decoder/wave.vcd
$date
	Fri Sep 12 11:31:06 2025
$end
$version
	Icarus Verilog
$end
$timescale
	1ns
$end
$scope module decoder_tb $end
$var wire 16 ! y [15:0] $end
$var reg 4 " d [3:0] $end
$var reg 1 # e $end
$var integer 32 $ i [31:0] $end
$scope module dut $end
$var wire 4 % d [3:0] $end
$var wire 1 # e $end
$var wire 16 & y [15:0] $end
$upscope $end
$upscope $end
$enddefinitions $end
$comment Show the parameter values. $end
$dumpall
$end
#0
$dumpvars
b0 &
b0 %
bx $
0#
b0 "
b0 !
$end
#1
b1011 "
b1011 %
#2
b100000000000 !
b100000000000 &
1#
#3
b0 $
#4
b1 !
b1 &
b1 $
b0 "
b0 %
#5
b10 !
b10 &
b10 $
b1 "
b1 %
#6
b100 !
b100 &
b11 $
b10 "
b10 %
#7
b1000 !
b1000 &
b100 $
b11 "
b11 %
#8
b10000 !
b10000 &
b101 $
b100 "
b100 %
#9
b100000 !
b100000 &
b110 $
b101 "
b101 %
#10
b1000000 !
b1000000 &
b111 $
b110 "
b110 %
#11
b10000000 !
b10000000 &
b1000 $
b111 "
b111 %
#12
b100000000 !
b100000000 &
b1001 $
b1000 "
b1000 %
#13
b1000000000 !
b1000000000 &
b1010 $
b1001 "
b1001 %
#14
b10000000000 !
b10000000000 &
b1011 $
b1010 "
b1010 %
#15
b100000000000 !
b100000000000 &
b1100 $
b1011 "
b1011 %
#16
b1000000000000 !
b1000000000000 &
b1101 $
b1100 "
b1100 %
#17
b10000000000000 !
b10000000000000 &
b1110 $
b1101 "
b1101 %
#18
b100000000000000 !
b100000000000000 &
b1111 $
b1110 "
b1110 %
#19
b1000000000000000 !
b1000000000000000 &
b10000 $
b1111 "
b1111 %
