fulladder/full_adder.v
module full_adder(input a,b,cin, output sum,carry);
assign sum=a^b^cin;
assign carry=(a&b)|(b&cin)|(a&cin);
endmodule

fulladder/full_adder_tb.v
module test;
reg a,b,cin;
wire sum,carry;
full_adder dut(.a(a),.b(b),.cin(cin),.sum(sum),.carry(carry));
initial begin
    $dumpfile("wave.vcd");
    $dumpvars(0,test);

    a=0; b=0 ;cin=0;
    #10 a=0; b=0 ;cin=1;
    #10 a=0; b=1 ;cin=0;
    #10 a=0; b=1 ;cin=1;
    #10 a=1; b=0 ;cin=0;
    #10 a=1; b=0 ;cin=1;
    #10 a=1; b=1 ;cin=0;
    #10 a=1; b=1 ;cin=1;
    #80 $finish;
 end
 always @(a or b or cin)
 $display("time=%0t INPUT:a=%b b=%b cin=%b OUTPUT:summ=%b carry=%b",$time,a,b,cin,sum,carry);
 endmodule

fulladder/wave.vcd
$date
	Mon Aug 11 21:00:02 2025
$end
$version
	Icarus Verilog
$end
$timescale
	1s
$end
$scope module test $end
$var wire 1 ! sum $end
$var wire 1 " carry $end
$var reg 1 # a $end
$var reg 1 $ b $end
$var reg 1 % cin $end
$scope module dut $end
$var wire 1 # a $end
$var wire 1 $ b $end
$var wire 1 " carry $end
$var wire 1 % cin $end
$var wire 1 ! sum $end
$upscope $end
$upscope $end
$enddefinitions $end
$comment Show the parameter values. $end
$dumpall
$end
#0
$dumpvars
0%
0$
0#
0"
0!
$end
#10
1!
1%
#20
0%
1$
#30
1"
0!
1%
#40
0"
1!
0%
0$
1#
#50
1"
0!
1%
#60
0%
1$
#70
1!
1%
