oct_binary/oct_binary.v
module oct_binary(input[7:0]d,//behaviout modelling
output reg[2:0]y);
always @(*) begin
 case(d)
 8'b0000_0001:y=3'd0;  //8-8 bit input  3-3 bit output
 8'b0000_0010:y=3'd1;
 8'b0000_0100:y=3'd2;
 8'b0000_1000:y=3'd3;
 8'b0001_0000:y=3'd4;
 8'b0010_0000:y=3'd5;
 8'b0100_0000:y=3'd6;
 8'b1000_0000:y=3'd7;
 default:begin
    y=8'bxxx;
    $display("INVALID");
 end
 endcase
end
endmodule

oct_binary/oct_binary_tb.v
module test;
reg[7:0]d;
wire[2:0]y;
oct_binary dut(.d(d),.y(y));
initial begin
    $dumpfile("wave.vcd");
    $dumpvars(0,test);
    d=8'b0000_0001;  //8-8 bit input  3-3 bit output
    #2 d=8'b0000_0010;
    #2 d=8'b0000_0100;
    #2 d=8'b0000_1000;
    #2 d=8'b0001_0000;
    #2 d=8'b0010_0000;
    #2 d=8'b0100_0000;
    #2 d=8'b1000_0000;
    #30 $finish;
end
always @(d)
$display("time=%0t INPUT=%b OUTPUT=%b",$time,d,y);
endmodule

oct_binary/wave.vcd
$date
	Wed Sep 10 11:32:19 2025
$end
$version
	Icarus Verilog
$end
$timescale
	1s
$end
$scope module test $end
$var wire 3 ! y [2:0] $end
$var reg 8 " d [7:0] $end
$scope module dut $end
$var wire 8 # d [7:0] $end
$var reg 3 $ y [2:0] $end
$upscope $end
$upscope $end
$enddefinitions $end
$comment Show the parameter values. $end
$dumpall
$end
#0
$dumpvars
b0 $
b1 #
b1 "
b0 !
$end
#2
b1 !
b1 $
b10 "
b10 #
#4
b10 !
b10 $
b100 "
b100 #
#6
b11 !
b11 $
b1000 "
b1000 #
#8
b100 !
b100 $
b10000 "
b10000 #
#10
b101 !
b101 $
b100000 "
b100000 #
#12
b110 !
b110 $
b1000000 "
b1000000 #
#14
b111 !
b111 $
b10000000 "
b10000000 #
