priorityencoder8x3/priority_encoder.v
module priority_encoder(input[7:0]d,  //behaviour modelling
output reg[2:0]y);
always @(*) begin
    casex(d)
    8'b0000_0000:y=3'b000;
    8'b0000_001x:y=3'b001;
    8'b0000_01xx:y=3'b010;
    8'b0000_1xxx:y=3'b011;
    8'b0001_xxxx:y=3'b100;
    8'b001x_xxxx:y=3'b101;
    8'b01xx_xxxx:y=3'b110;
    8'b1xxx_xxxx:y=3'b111;
    default:begin
        y=3'bxxx;
        $display("INVALID");
    end
endcase
end

endmodule

priorityencoder8x3/priority_encoder_tb.v
module test;
reg[7:0]d;
wire[2:0]y;
priority_encoder uut(.d(d),.y(y));
initial begin
    $dumpfile("wave.vcd");
    $dumpvars(0,test);

    d=0;
    
      d=8'b0000_0001;#10
      d=8'b0000_0010;#10
      d=8'b0000_0100;#10
      d=8'b0000_1000;#10
      d=8'b0001_0000;#10
      d=8'b0010_0000;#10
      d=8'b0100_0000;#10
      d=8'b1000_0000;#10
    #10 $finish;
end
always @(d or y)
$monitor("time=%0t INPUT =%b OUTPUT =%b",$time,d,y);
endmodule

priorityencoder8x3/wave.vcd
$date
	Wed Sep 10 20:27:21 2025
$end
$version
	Icarus Verilog
$end
$timescale
	1s
$end
$scope module test $end
$var wire 3 ! y [2:0] $end
$var reg 8 " d [7:0] $end
$scope module uut $end
$var wire 8 # d [7:0] $end
$var reg 3 $ y [2:0] $end
$upscope $end
$upscope $end
$enddefinitions $end
$comment Show the parameter values. $end
$dumpall
$end
#0
$dumpvars
bx $
b1 #
b1 "
bx !
$end
#10
b1 !
b1 $
b10 "
b10 #
#20
b10 !
b10 $
b100 "
b100 #
#30
b11 !
b11 $
b1000 "
b1000 #
#40
b100 !
b100 $
b10000 "
b10000 #
#50
b101 !
b101 $
b100000 "
b100000 #
#60
b110 !
b110 $
b1000000 "
b1000000 #
#70
b111 !
b111 $
b10000000 "
b10000000 #
