srflipflop/sr.v
module SR_flipflop(input s,r,clk,rst,
output reg q,
output qbar);
always @(posedge clk)begin
    if(rst)
    q<=0;
    else begin
        case({s,r})
        2'b00:q<=q;
        2'b01:q<=1'b0;
        2'b10:q<=1'b1; 
        2'b11:q<=1'bx;
    endcase
    end 
end
assign qbar=~q;
endmodule

srflipflop/sr_tb.v
module test;
reg s,r,clk,rst;
wire q,qbar;
SR_flipflop dut(s,r,clk,rst,q,qbar);
always #2 clk=~clk;

initial begin
    clk=0;
    rst=1;
    #4 rst=0;
    $display("reset=%0h q=%0h qbar=%0h",rst,q,qbar);
    drive(2'b00);
    drive(2'b01);
    drive(2'b10);
    drive(2'b11);
    #50 $finish;
end
initial begin
    $dumpfile("wave.vcd");
    $dumpvars(0,test);
end
task drive;
input[1:0]a;
begin
@(posedge clk);
{s,r}=a;
#1 $display("s=%0h,r=%0h q=%0h qbar=%0h",s,r,q,qbar);
end
endtask
endmodule

srflipflop/wave.vcd
$date
	Mon Sep 15 12:18:21 2025
$end
$version
	Icarus Verilog
$end
$timescale
	1s
$end
$scope module test $end
$var wire 1 ! qbar $end
$var wire 1 " q $end
$var reg 1 # clk $end
$var reg 1 $ r $end
$var reg 1 % rst $end
$var reg 1 & s $end
$scope module dut $end
$var wire 1 # clk $end
$var wire 1 ! qbar $end
$var wire 1 $ r $end
$var wire 1 % rst $end
$var wire 1 & s $end
$var reg 1 " q $end
$upscope $end
$scope task drive $end
$var reg 2 ' a [1:0] $end
$upscope $end
$upscope $end
$enddefinitions $end
$comment Show the parameter values. $end
$dumpall
$end
#0
$dumpvars
bx '
x&
1%
x$
0#
x"
x!
$end
#2
1!
0"
1#
#4
0#
b0 '
0%
#6
0&
0$
1#
#7
b1 '
#8
0#
#10
1$
1#
#11
b10 '
#12
0#
#14
0!
1"
1&
0$
1#
#15
b11 '
#16
0#
#18
x!
x"
1$
1#
